shopify_scrape/__init__.py
shopify_scrape/extract.py
shopify_scrape/utils.py
tests/__init__.py
tests/test_extract.py
tests/test_utils.py
shopify_scrape-0.0.5.dist-info/LICENSE
shopify_scrape-0.0.5.dist-info/METADATA
shopify_scrape-0.0.5.dist-info/WHEEL
shopify_scrape-0.0.5.dist-info/top_level.txt
shopify_scrape-0.0.5.dist-info/RECORD
