Metadata-Version: 2.1
Name: shopify-scrape
Version: 0.0.5
Summary: Python module to scrape Shopify store URLs
Home-page: https://github.com/loren-jiang/shopify-scrape
Author: Loren Jiang
Author-email: loren.jiang@gmail.com
License: UNKNOWN
Platform: UNKNOWN
Classifier: Programming Language :: Python :: 3
Classifier: License :: OSI Approved :: MIT License
Classifier: Operating System :: OS Independent
Requires-Python: >=3.7
Requires-Dist: requests
